chenyang/Love.py
chenyang/__init__.py
chenyang/apple.py
chenyang-1.0.9.dist-info/METADATA
chenyang-1.0.9.dist-info/WHEEL
chenyang-1.0.9.dist-info/top_level.txt
chenyang-1.0.9.dist-info/RECORD
